<rows>
  <row term_id="1133200" id="1133447" title="About MyPART" langcode="en" field_short_title="About" field_page_description="MyPART, the My Pediatric and Adult Rare Tumor network, is a group of scientists, patients, family members, advocates, and healthcare providers who want to help find treatments for rare cancers." field_list_description="MyPART, the My Pediatric and Adult Rare Tumor network, is a group of scientists, patients, family members, advocates, and healthcare providers who want to help find treatments for rare cancers." field_search_engine_restrictions="IncludeSearch" field_public_use="0" field_date_posted="2019-02-27" field_date_reviewed="2018-12-20" field_date_updated="2018-12-20" field_browser_title="About" field_card_title="About">
    <intro><![CDATA[<div class="rxbodyfield">
<p>Find out more about what we do, who we are, and how to contact us for more information.</p>
</div>]]></intro>
    <related_resource_ids>
      <related_resource_ids xmlns="">7249559</related_resource_ids>
      <SORT_RANK xmlns="">1</SORT_RANK>
      <related_resource_ids xmlns="">7192214</related_resource_ids>
      <SORT_RANK xmlns="">2</SORT_RANK>
      <related_resource_ids xmlns="">7192215</related_resource_ids>
      <SORT_RANK xmlns="">3</SORT_RANK>
    </related_resource_ids>
    <field_landing_contents>
      <field_landing_contents xmlns="">1143447</field_landing_contents>
      <field_landing_contents xmlns="">1133447</field_landing_contents>
    </field_landing_contents>
  </row>
  <row term_id="1133192" id="1133526" title="Research" langcode="en" field_short_title="Research" field_page_description="MyPART is working to address the challenges researchers face in studying rare cancers so we can find new treatments faster." field_feature_card_description="MyPART is working to address the challenges researchers face in studying rare cancers." field_list_description="MyPART is working to address the challenges researchers face in studying rare cancers so we can find new treatments faster." field_search_engine_restrictions="IncludeSearch" field_public_use="0" field_date_posted="2018-12-20" field_date_reviewed="2018-12-20" field_date_updated="2018-12-20" field_browser_title="Research" field_card_title="Research">
    <intro><![CDATA[<div class="rxbodyfield">
<p>Research is key to finding new treatments for rare cancers. Researchers studying rare cancers face a lot of challenges. MyPART is working to address these challenges&nbsp;in hopes of&nbsp;finding new treatments faster.</p>
</div>]]></intro>
    <related_resource_ids>
      <related_resource_ids xmlns="">7328894</related_resource_ids>
      <SORT_RANK xmlns="">0</SORT_RANK>
      <related_resource_ids xmlns="">7328895</related_resource_ids>
      <SORT_RANK xmlns="">1</SORT_RANK>
    </related_resource_ids>
    <field_landing_contents>
      <field_landing_contents xmlns="">1143526</field_landing_contents>
      <field_landing_contents xmlns="">1133526</field_landing_contents>
    </field_landing_contents>
  </row>
  <row term_id="1133198" id="1133528" title="News" langcode="en" field_short_title="News" field_page_description="The latest news and clinics from MyPART." field_feature_card_description="MyPART hosts events and participates in scientific conferences that help promote rare tumor research." field_list_description="The latest news and clinics from MyPART." field_search_engine_restrictions="IncludeSearch" field_public_use="0" field_date_posted="2018-12-20" field_date_reviewed="2018-12-20" field_date_updated="2018-12-20" field_browser_title="News" field_card_title="News">
    <intro><![CDATA[<div class="rxbodyfield">
<p>MyPART hosts events and participates in scientific conferences that help promote rare tumor research. Check back often to read news about MyPART activities and upcoming events.</p>
</div>]]></intro>
    <related_resource_ids>
      <related_resource_ids xmlns="">7337551</related_resource_ids>
      <SORT_RANK xmlns="">0</SORT_RANK>
      <related_resource_ids xmlns="">7337550</related_resource_ids>
      <SORT_RANK xmlns="">1</SORT_RANK>
      <related_resource_ids xmlns="">7337552</related_resource_ids>
      <SORT_RANK xmlns="">2</SORT_RANK>
    </related_resource_ids>
    <field_landing_contents>
      <field_landing_contents xmlns="">1143528</field_landing_contents>
      <field_landing_contents xmlns="">1133528</field_landing_contents>
    </field_landing_contents>
  </row>
  <row term_id="1133174" id="1133525" title="Rare Tumors" langcode="en" field_short_title="Rare Tumors" field_page_description="Rare tumors can form anywhere in the body. MyPART is studying tumors in several different body systems. " field_list_description="Rare tumors can form anywhere in the body. MyPART is studying tumors in several different body systems. " field_search_engine_restrictions="IncludeSearch" field_public_use="0" field_date_posted="2018-12-20" field_date_reviewed="2018-12-20" field_date_updated="2018-12-20" field_browser_title="Rare Tumors" field_card_title="MyPART Rare Tumors">
    <intro><![CDATA[<div class="rxbodyfield">
<p>Rare tumors can form anywhere in the body. MyPART is studying tumors in several different body systems.</p>
</div>]]></intro>
    <field_landing_contents>
      <field_landing_contents xmlns="">1143525</field_landing_contents>
      <field_landing_contents xmlns="">1153525</field_landing_contents>
      <field_landing_contents xmlns="">1173525</field_landing_contents>
    </field_landing_contents>
  </row>
</rows>