{
  "chartSubTitle":{
    "text":"Fiscal Year 2023"
  },
  "chartTitle":{
    "text":"FY 2023 Cancer Moonshot and Carryover - Obligations by Mechanism"
  },
  "chartType":{
    "type":"NCI_pie"
  },
  "drilldown":{
    "series":[
      {
        "name":"Research Project Grants",
        "id":"Research Grants",
        "colors":[
          "#2DC799",
          "#ABE9D6",
          "#229573",
          "#17644D",
          "#D5F4EB",
          "#0B3226"
        ],
        "data":[
          [
            "RPGs",
            38994370
          ],
          [
            "Centers",
            22743859
          ],
          [
            "Other Research",
            29363630
          ]
        ]
      },
      {
        "name":"R&D Contract",
        "id":"R&D Contracts",
        "colors":[
          "#FF5F00",
          "#FFBF99"
        ],
        "data":[
          [
            "R&D Contracts",
            19241154
          ],
          [
            "SBIR/STTR Contracts",
            6739920
          ]
        ]
      }
    ]
  },
  "series":[
    {
      "name":"Budget",
      "data":[
        {
          "name":"Research Grants",
          "y":91101859,
          "drilldown":"Research Grants"
        },
        {
          "name":"Intramural Research",
          "y":7086652
        },
        {
          "name":"R&D Contracts",
          "y":25981074,
          "drilldown":"R&D Contracts"
        },
        {
          "name":"Research Management & Support",
          "y":236744
        }
      ]
    }
  ]
}
