<rows>
  <row>
    <id>898666</id>
    <field_cthp_card_title>Coping with Cancer</field_cthp_card_title>
    <field_cthp_card_theme>cthp-general</field_cthp_card_theme>
    <langcode>en</langcode>
    <field_cthp_block_card_content>1115050</field_cthp_block_card_content>
  </row>
  <row>
    <id>918819</id>
    <field_cthp_card_title>Cómo hacer frente al cáncer</field_cthp_card_title>
    <field_cthp_card_theme>cthp-general</field_cthp_card_theme>
    <langcode>es</langcode>
    <field_cthp_block_card_content>1115053</field_cthp_block_card_content>
  </row>
  <row>
    <id>1031776</id>
    <field_cthp_card_title>Supportive &amp; Palliative Care</field_cthp_card_title>
    <field_cthp_card_theme>cthp-general</field_cthp_card_theme>
    <langcode>en</langcode>
    <field_cthp_block_card_content>1115049</field_cthp_block_card_content>
  </row>
  <row>
    <id>1031777</id>
    <field_cthp_card_title>Cuidados médicos de apoyo</field_cthp_card_title>
    <field_cthp_card_theme>cthp-general</field_cthp_card_theme>
    <langcode>es</langcode>
    <field_cthp_block_card_content>1115052</field_cthp_block_card_content>
  </row>
</rows>
